hashimportai/__init__.py
hashimportai/client.py
hashimportai/errors.py
hashimportai/executor.py
hashimportai/runner.py
hashimportai/validator.py
hashimportai-0.1.1.dist-info/licenses/LICENSE
hashimportai-0.1.1.dist-info/METADATA
hashimportai-0.1.1.dist-info/WHEEL
hashimportai-0.1.1.dist-info/top_level.txt
hashimportai-0.1.1.dist-info/RECORD
