Metadata-Version: 2.4
Name: hashimportai
Version: 0.1.1
Summary: Manifest-driven workflow execution SDK for HashImport
Author-email: Narayan <your-email@domain.com>
License: MIT License
Project-URL: Homepage, https://github.com/yourorg/hashimportai
Project-URL: Documentation, https://github.com/yourorg/hashimportai#readme
Project-URL: Source, https://github.com/yourorg/hashimportai
Project-URL: Issues, https://github.com/yourorg/hashimportai/issues
Keywords: workflow,orchestration,pdf,esign,hashimport,automation,sdk
Classifier: Programming Language :: Python :: 3
Classifier: License :: OSI Approved :: MIT License
Classifier: Operating System :: OS Independent
Classifier: Intended Audience :: Developers
Classifier: Topic :: Software Development :: Libraries
Requires-Python: >=3.9
License-File: LICENSE
Requires-Dist: httpx>=0.24.0
Dynamic: license-file
